DAwandb/__init__.py
DAwandb/main.py
DAwandb/main2.py
DAwandb-0.0.1.dist-info/METADATA
DAwandb-0.0.1.dist-info/WHEEL
DAwandb-0.0.1.dist-info/top_level.txt
DAwandb-0.0.1.dist-info/RECORD
